<?xml version="1.0" encoding="utf-8" standalone="yes"?>
<Gesture Name="RotateRight9" Subject="test" Speed="test" NumPts="74" Milliseconds="1061" AppName="Recognizer.NDollar" AppVer="8.1.2012.0" Date="Monday, November 16, 2015" TimeOfDay="5:53:51 PM">
  <Stroke index="1">
    <Point X="182" Y="217" T="151681051" />
    <Point X="181" Y="217" T="151681098" />
    <Point X="178" Y="217" T="151681098" />
    <Point X="176" Y="217" T="151681113" />
    <Point X="173" Y="217" T="151681129" />
    <Point X="170" Y="217" T="151681144" />
    <Point X="166" Y="217" T="151681160" />
    <Point X="163" Y="217" T="151681176" />
    <Point X="157" Y="217" T="151681191" />
    <Point X="149" Y="217" T="151681207" />
    <Point X="142" Y="217" T="151681222" />
    <Point X="138" Y="217" T="151681238" />
    <Point X="135" Y="217" T="151681238" />
    <Point X="132" Y="217" T="151681254" />
    <Point X="128" Y="217" T="151681285" />
    <Point X="126" Y="217" T="151681300" />
    <Point X="123" Y="215" T="151681300" />
    <Point X="119" Y="214" T="151681316" />
    <Point X="115" Y="213" T="151681332" />
    <Point X="113" Y="212" T="151681347" />
    <Point X="112" Y="212" T="151681363" />
    <Point X="110" Y="211" T="151681378" />
    <Point X="107" Y="211" T="151681394" />
    <Point X="106" Y="210" T="151681425" />
    <Point X="106" Y="209" T="151681425" />
    <Point X="105" Y="207" T="151681441" />
    <Point X="105" Y="206" T="151681456" />
    <Point X="105" Y="203" T="151681472" />
    <Point X="105" Y="199" T="151681503" />
    <Point X="105" Y="193" T="151681503" />
    <Point X="105" Y="185" T="151681519" />
    <Point X="106" Y="179" T="151681534" />
    <Point X="106" Y="176" T="151681550" />
    <Point X="106" Y="173" T="151681550" />
    <Point X="106" Y="170" T="151681566" />
    <Point X="106" Y="167" T="151681597" />
    <Point X="107" Y="164" T="151681597" />
    <Point X="108" Y="161" T="151681628" />
    <Point X="108" Y="157" T="151681628" />
    <Point X="108" Y="152" T="151681644" />
    <Point X="108" Y="145" T="151681659" />
    <Point X="108" Y="139" T="151681675" />
    <Point X="108" Y="136" T="151681690" />
    <Point X="108" Y="133" T="151681706" />
    <Point X="108" Y="129" T="151681706" />
    <Point X="108" Y="124" T="151681722" />
    <Point X="108" Y="122" T="151681737" />
    <Point X="108" Y="119" T="151681753" />
    <Point X="108" Y="116" T="151681753" />
    <Point X="108" Y="113" T="151681768" />
    <Point X="108" Y="111" T="151681784" />
    <Point X="109" Y="109" T="151681800" />
    <Point X="110" Y="107" T="151681815" />
    <Point X="110" Y="106" T="151681831" />
    <Point X="111" Y="104" T="151681846" />
    <Point X="113" Y="103" T="151681862" />
    <Point X="114" Y="101" T="151681878" />
    <Point X="116" Y="99" T="151681893" />
    <Point X="117" Y="98" T="151681893" />
    <Point X="118" Y="96" T="151681909" />
    <Point X="118" Y="95" T="151681940" />
    <Point X="120" Y="94" T="151681940" />
    <Point X="123" Y="93" T="151681956" />
    <Point X="126" Y="91" T="151681971" />
    <Point X="130" Y="89" T="151681987" />
    <Point X="134" Y="88" T="151682002" />
    <Point X="140" Y="86" T="151682018" />
    <Point X="146" Y="85" T="151682034" />
    <Point X="149" Y="83" T="151682034" />
    <Point X="154" Y="82" T="151682065" />
    <Point X="159" Y="80" T="151682080" />
    <Point X="166" Y="78" T="151682080" />
    <Point X="175" Y="77" T="151682096" />
    <Point X="183" Y="75" T="151682112" />
  </Stroke>
</Gesture>